datasette_pretty_json/__init__.py
datasette_pretty_json-0.3.dist-info/LICENSE
datasette_pretty_json-0.3.dist-info/METADATA
datasette_pretty_json-0.3.dist-info/WHEEL
datasette_pretty_json-0.3.dist-info/entry_points.txt
datasette_pretty_json-0.3.dist-info/top_level.txt
datasette_pretty_json-0.3.dist-info/RECORD
