Metadata-Version: 2.1
Name: datasette-pretty-json
Version: 0.3
Summary: Datasette plugin that pretty-prints any column values that are valid JSON objects or arrays
Home-page: https://github.com/simonw/datasette-pretty-json
Author: Simon Willison
License: Apache License, Version 2.0
License-File: LICENSE
Requires-Dist: datasette
Provides-Extra: test
Requires-Dist: pytest ; extra == 'test'
